{
    "agosto": {
        "Alejandro Korn": {
            "fuente": "https://www.instagram.com/farmaciamatayoshiok/",
            "confianza": 3,
            "dias": {
                "1": [
                    {
                        "nombre": "ALKORN",
                        "direccion": "H. Hyrigoyen 30513, Alejandro Korn, Provincia de Buenos Aires, Argentina",
                        "telefono": "",
                        "mapa": "https://www.google.com/maps/search/H.+Hyrigoyen+30513,+Alejandro+Korn,+Provincia+de+Buenos+Aires,+Argentina"
                    }
                ],
                "2": [
                    {
                        "nombre": "PETRUCCI",
                        "direccion": "San Martin 199, Alejandro Korn, Provincia de Buenos Aires, Argentina",
                        "telefono": "",
                        "mapa": "https://www.google.com/maps/search/San+Martin+199,+Alejandro+Korn,+Provincia+de+Buenos+Aires,+Argentina"
                    }
                ],
                "3": [
                    {
                        "nombre": "TODO NV",
                        "direccion": "H. Hyrigoyen 29701, Alejandro Korn, Provincia de Buenos Aires, Argentina",
                        "telefono": "",
                        "mapa": "https://www.google.com/maps/search/H.+Hyrigoyen+29701,+Alejandro+Korn,+Provincia+de+Buenos+Aires,+Argentina"
                    }
                ],
                "4": [
                    {
                        "nombre": "MATAYOSHI (CASAS)",
                        "direccion": "P. Perón 4702, Alejandro Korn, Provincia de Buenos Aires, Argentina",
                        "telefono": "2225 52 9629",
                        "mapa": "https://www.google.com/maps/search/P.+Perón+4702,+Alejandro+Korn,+Provincia+de+Buenos+Aires,+Argentina"
                    }
                ],
                "5": [
                    {
                        "nombre": "TODO NV",
                        "direccion": "H. Hyrigoyen 29701, Alejandro Korn, Provincia de Buenos Aires, Argentina",
                        "telefono": "",
                        "mapa": "https://www.google.com/maps/search/H.+Hyrigoyen+29701,+Alejandro+Korn,+Provincia+de+Buenos+Aires,+Argentina"
                    }
                ],
                "6": [
                    {
                        "nombre": "FIOTEK",
                        "direccion": "J.M. de Rosas Nº 325, Alejandro Korn, Provincia de Buenos Aires, Argentina",
                        "telefono": "",
                        "mapa": "https://www.google.com/maps/search/J.M.+de+Rosas+Nº+325,+Alejandro+Korn,+Provincia+de+Buenos+Aires,+Argentina"
                    }
                ],
                "7": [
                    {
                        "nombre": "ALKORN",
                        "direccion": "H. Hyrigoyen 30513, Alejandro Korn, Provincia de Buenos Aires, Argentina",
                        "telefono": "",
                        "mapa": "https://www.google.com/maps/search/H.+Hyrigoyen+30513,+Alejandro+Korn,+Provincia+de+Buenos+Aires,+Argentina"
                    }
                ],
                "8": [
                    {
                        "nombre": "PETRUCCI",
                        "direccion": "San Martin 199, Alejandro Korn, Provincia de Buenos Aires, Argentina",
                        "telefono": "",
                        "mapa": "https://www.google.com/maps/search/San+Martin+199,+Alejandro+Korn,+Provincia+de+Buenos+Aires,+Argentina"
                    }
                ],
                "9": [
                    {
                        "nombre": "PUNTO DE SALUD",
                        "direccion": "Independencia 111, Alejandro Korn, Provincia de Buenos Aires, Argentina",
                        "telefono": "",
                        "mapa": "https://www.google.com/maps/search/Independencia+111,+Alejandro+Korn,+Provincia+de+Buenos+Aires,+Argentina"
                    }
                ],
                "10": [
                    {
                        "nombre": "MATAYOSHI (CASAS)",
                        "direccion": "P. Perón 4702, Alejandro Korn, Provincia de Buenos Aires, Argentina",
                        "telefono": "2225 52 9629",
                        "mapa": "https://www.google.com/maps/search/P.+Perón+4702,+Alejandro+Korn,+Provincia+de+Buenos+Aires,+Argentina"
                    }
                ],
                "11": [
                    {
                        "nombre": "TODO NV",
                        "direccion": "H. Hyrigoyen 29701, Alejandro Korn, Provincia de Buenos Aires, Argentina",
                        "telefono": "",
                        "mapa": "https://www.google.com/maps/search/H.+Hyrigoyen+29701,+Alejandro+Korn,+Provincia+de+Buenos+Aires,+Argentina"
                    }
                ],
                "12": [
                    {
                        "nombre": "FIOTEK",
                        "direccion": "J.M. de Rosas Nº 325, Alejandro Korn, Provincia de Buenos Aires, Argentina",
                        "telefono": "",
                        "mapa": "https://www.google.com/maps/search/J.M.+de+Rosas+Nº+325,+Alejandro+Korn,+Provincia+de+Buenos+Aires,+Argentina"
                    }
                ],
                "13": [
                    {
                        "nombre": "ALKORN",
                        "direccion": "H. Hyrigoyen 30513, Alejandro Korn, Provincia de Buenos Aires, Argentina",
                        "telefono": "",
                        "mapa": "https://www.google.com/maps/search/H.+Hyrigoyen+30513,+Alejandro+Korn,+Provincia+de+Buenos+Aires,+Argentina"
                    }
                ],
                "14": [
                    {
                        "nombre": "PETRUCCI",
                        "direccion": "San Martin 199, Alejandro Korn, Provincia de Buenos Aires, Argentina",
                        "telefono": "",
                        "mapa": "https://www.google.com/maps/search/San+Martin+199,+Alejandro+Korn,+Provincia+de+Buenos+Aires,+Argentina"
                    }
                ],
                "15": [
                    {
                        "nombre": "PUNTO DE SALUD",
                        "direccion": "Independencia 111, Alejandro Korn, Provincia de Buenos Aires, Argentina",
                        "telefono": "",
                        "mapa": "https://www.google.com/maps/search/Independencia+111,+Alejandro+Korn,+Provincia+de+Buenos+Aires,+Argentina"
                    }
                ],
                "16": [
                    {
                        "nombre": "MATAYOSHI (CASAS)",
                        "direccion": "P. Perón 4702, Alejandro Korn, Provincia de Buenos Aires, Argentina",
                        "telefono": "2225 52 9629",
                        "mapa": "https://www.google.com/maps/search/P.+Perón+4702,+Alejandro+Korn,+Provincia+de+Buenos+Aires,+Argentina"
                    }
                ],
                "17": [
                    {
                        "nombre": "TODO NV",
                        "direccion": "H. Hyrigoyen 29701, Alejandro Korn, Provincia de Buenos Aires, Argentina",
                        "telefono": "",
                        "mapa": "https://www.google.com/maps/search/H.+Hyrigoyen+29701,+Alejandro+Korn,+Provincia+de+Buenos+Aires,+Argentina"
                    }
                ],
                "18": [
                    {
                        "nombre": "FIOTEK",
                        "direccion": "J.M. de Rosas Nº 325, Alejandro Korn, Provincia de Buenos Aires, Argentina",
                        "telefono": "",
                        "mapa": "https://www.google.com/maps/search/J.M.+de+Rosas+Nº+325,+Alejandro+Korn,+Provincia+de+Buenos+Aires,+Argentina"
                    }
                ],
                "19": [
                    {
                        "nombre": "ALKORN",
                        "direccion": "H. Hyrigoyen 30513, Alejandro Korn, Provincia de Buenos Aires, Argentina",
                        "telefono": "",
                        "mapa": "https://www.google.com/maps/search/H.+Hyrigoyen+30513,+Alejandro+Korn,+Provincia+de+Buenos+Aires,+Argentina"
                    }
                ],
                "20": [
                    {
                        "nombre": "PETRUCCI",
                        "direccion": "San Martin 199, Alejandro Korn, Provincia de Buenos Aires, Argentina",
                        "telefono": "",
                        "mapa": "https://www.google.com/maps/search/San+Martin+199,+Alejandro+Korn,+Provincia+de+Buenos+Aires,+Argentina"
                    }
                ],
                "21": [
                    {
                        "nombre": "PUNTO DE SALUD",
                        "direccion": "Independencia 111, Alejandro Korn, Provincia de Buenos Aires, Argentina",
                        "telefono": "",
                        "mapa": "https://www.google.com/maps/search/Independencia+111,+Alejandro+Korn,+Provincia+de+Buenos+Aires,+Argentina"
                    }
                ],
                "22": [
                    {
                        "nombre": "MATAYOSHI (CASAS)",
                        "direccion": "P. Perón 4702, Alejandro Korn, Provincia de Buenos Aires, Argentina",
                        "telefono": "2225 52 9629",
                        "mapa": "https://www.google.com/maps/search/P.+Perón+4702,+Alejandro+Korn,+Provincia+de+Buenos+Aires,+Argentina"
                    }
                ],
                "23": [
                    {
                        "nombre": "TODO NV",
                        "direccion": "H. Hyrigoyen 29701, Alejandro Korn, Provincia de Buenos Aires, Argentina",
                        "telefono": "",
                        "mapa": "https://www.google.com/maps/search/H.+Hyrigoyen+29701,+Alejandro+Korn,+Provincia+de+Buenos+Aires,+Argentina"
                    }
                ],
                "24": [
                    {
                        "nombre": "FIOTEK",
                        "direccion": "J.M. de Rosas Nº 325, Alejandro Korn, Provincia de Buenos Aires, Argentina",
                        "telefono": "",
                        "mapa": "https://www.google.com/maps/search/J.M.+de+Rosas+Nº+325,+Alejandro+Korn,+Provincia+de+Buenos+Aires,+Argentina"
                    }
                ],
                "25": [
                    {
                        "nombre": "ALKORN",
                        "direccion": "H. Hyrigoyen 30513, Alejandro Korn, Provincia de Buenos Aires, Argentina",
                        "telefono": "",
                        "mapa": "https://www.google.com/maps/search/H.+Hyrigoyen+30513,+Alejandro+Korn,+Provincia+de+Buenos+Aires,+Argentina"
                    }
                ],
                "26": [
                    {
                        "nombre": "PETRUCCI",
                        "direccion": "San Martin 199, Alejandro Korn, Provincia de Buenos Aires, Argentina",
                        "telefono": "",
                        "mapa": "https://www.google.com/maps/search/San+Martin+199,+Alejandro+Korn,+Provincia+de+Buenos+Aires,+Argentina"
                    }
                ],
                "27": [
                    {
                        "nombre": "PUNTO DE SALUD",
                        "direccion": "Independencia 111, Alejandro Korn, Provincia de Buenos Aires, Argentina",
                        "telefono": "",
                        "mapa": "https://www.google.com/maps/search/Independencia+111,+Alejandro+Korn,+Provincia+de+Buenos+Aires,+Argentina"
                    }
                ],
                "28": [
                    {
                        "nombre": "MATAYOSHI (CASAS)",
                        "direccion": "P. Perón 4702, Alejandro Korn, Provincia de Buenos Aires, Argentina",
                        "telefono": "2225 52 9629",
                        "mapa": "https://www.google.com/maps/search/P.+Perón+4702,+Alejandro+Korn,+Provincia+de+Buenos+Aires,+Argentina"
                    }
                ],
                "29": [
                    {
                        "nombre": "TODO NV",
                        "direccion": "H. Hyrigoyen 29701, Alejandro Korn, Provincia de Buenos Aires, Argentina",
                        "telefono": "",
                        "mapa": "https://www.google.com/maps/search/H.+Hyrigoyen+29701,+Alejandro+Korn,+Provincia+de+Buenos+Aires,+Argentina"
                    }
                ],
                "30": [
                    {
                        "nombre": "FIOTEK",
                        "direccion": "J.M. de Rosas Nº 325, Alejandro Korn, Provincia de Buenos Aires, Argentina",
                        "telefono": "",
                        "mapa": "https://www.google.com/maps/search/J.M.+de+Rosas+Nº+325,+Alejandro+Korn,+Provincia+de+Buenos+Aires,+Argentina"
                    }
                ],
                "31": [
                    {
                        "nombre": "ALKORN",
                        "direccion": "H. Hyrigoyen 30513, Alejandro Korn, Provincia de Buenos Aires, Argentina",
                        "telefono": "",
                        "mapa": "https://www.google.com/maps/search/H.+Hyrigoyen+30513,+Alejandro+Korn,+Provincia+de+Buenos+Aires,+Argentina"
                    }
                ]
            }
        }
    }
}